streamdeckapi/__init__.py
streamdeckapi/api.py
streamdeckapi/const.py
streamdeckapi/server.py
streamdeckapi/tools.py
streamdeckapi/types.py
streamdeckapi-0.0.13.dist-info/LICENSE
streamdeckapi-0.0.13.dist-info/METADATA
streamdeckapi-0.0.13.dist-info/WHEEL
streamdeckapi-0.0.13.dist-info/entry_points.txt
streamdeckapi-0.0.13.dist-info/top_level.txt
streamdeckapi-0.0.13.dist-info/RECORD
