Metadata-Version: 2.1
Name: streamdeckapi
Version: 0.0.13
Summary: Stream Deck API Library
Home-page: https://github.com/Patrick762/streamdeckapi
Author: Patrick762
Author-email: <pip-stream-deck-api@hosting-rt.de>
Classifier: Development Status :: 1 - Planning
Classifier: Intended Audience :: Developers
Classifier: Programming Language :: Python :: 3
Classifier: Operating System :: Unix
Classifier: Operating System :: MacOS :: MacOS X
Classifier: Operating System :: Microsoft :: Windows
License-File: LICENSE
Requires-Dist: requests
Requires-Dist: websockets>=13.1
Requires-Dist: aiohttp>=3.8
Requires-Dist: human-readable-ids==0.1.3
Requires-Dist: jsonpickle==3.0.1
Requires-Dist: streamdeck==0.9.3
Requires-Dist: pillow
Requires-Dist: cairosvg==2.7.0
Requires-Dist: zeroconf
